waddle/__init__.py
waddle/bunch.py
waddle/cli.py
waddle/param_bunch.py
waddle/settings.py
waddle/utils.py
waddle/version
waddle/aws/__init__.py
waddle/aws/pstore.py
waddle/aws/session.py
waddle-1.0.dist-info/METADATA
waddle-1.0.dist-info/WHEEL
waddle-1.0.dist-info/entry_points.txt
waddle-1.0.dist-info/top_level.txt
waddle-1.0.dist-info/zip-safe
waddle-1.0.dist-info/RECORD
