Metadata-Version: 2.1
Name: waddle
Version: 1.0
Summary: A pathy wrapper around aws parameter store
Home-page: https://github.com/angry-penguins/waddle
Author: Preetam Shingavi
Author-email: p.shingavi@yahoo.com
License: BSD
Keywords: aws python parameter-store kms
Platform: UNKNOWN
Classifier: Development Status :: 5 - Production/Stable
Classifier: Intended Audience :: Developers
Classifier: Topic :: Software Development :: Libraries :: Python Modules
Classifier: Programming Language :: Python :: 3
Classifier: Programming Language :: Python :: 3.6
Classifier: Programming Language :: Python :: 3.7
Classifier: License :: OSI Approved :: BSD License
Requires-Dist: pyyaml
Requires-Dist: boto3 (>=1.9.0)
Requires-Dist: click (>=7.0)
Requires-Dist: murmuration (>=0.7)
Requires-Dist: ruamel.yaml (>=0.15.87)
Requires-Dist: halo (>=0.0.26)
